[
  {
    "anonymous": false,
    "inputs": [
      {
        "indexed": true,
        "internalType": "address",
        "name": "logic",
        "type": "address"
      },
      {
        "indexed": true,
        "internalType": "bytes32",
        "name": "app",
        "type": "bytes32"
      },
      {
        "indexed": true,
        "internalType": "uint256",
        "name": "index",
        "type": "uint256"
      },
      {
        "indexed": false,
        "internalType": "address",
        "name": "token",
        "type": "address"
      }
    ],
    "name": "DTokenCreated",
    "type": "event"
  },
  {
    "anonymous": false,
    "inputs": [
      {
        "indexed": true,
        "internalType": "address",
        "name": "logic",
        "type": "address"
      },
      {
        "indexed": true,
        "internalType": "bytes32",
        "name": "app",
        "type": "bytes32"
      },
      {
        "indexed": true,
        "internalType": "address",
        "name": "pool",
        "type": "address"
      },
      {
        "indexed": false,
        "internalType": "address",
        "name": "cToken",
        "type": "address"
      },
      {
        "indexed": false,
        "internalType": "uint256",
        "name": "nTokens",
        "type": "uint256"
      }
    ],
    "name": "PoolCreated",
    "type": "event"
  },
  {
    "anonymous": false,
    "inputs": [
      {
        "indexed": true,
        "internalType": "address",
        "name": "origin",
        "type": "address"
      },
      {
        "indexed": true,
        "internalType": "bytes32",
        "name": "app",
        "type": "bytes32"
      },
      {
        "indexed": false,
        "internalType": "uint256",
        "name": "scaleLong",
        "type": "uint256"
      },
      {
        "indexed": false,
        "internalType": "uint256",
        "name": "scaleShort",
        "type": "uint256"
      }
    ],
    "name": "Deleverage",
    "type": "event"
  },
  {
    "anonymous": false,
    "inputs": [
      {
        "indexed": true,
        "internalType": "address",
        "name": "baseToken",
        "type": "address"
      },
      {
        "indexed": true,
        "internalType": "bytes32",
        "name": "app",
        "type": "bytes32"
      },
      {
        "indexed": true,
        "internalType": "address",
        "name": "cToken",
        "type": "address"
      },
      {
        "indexed": false,
        "internalType": "bytes32",
        "name": "baseSymbol",
        "type": "bytes32"
      },
      {
        "indexed": false,
        "internalType": "bytes32",
        "name": "quoteSymbol",
        "type": "bytes32"
      },
      {
        "indexed": false,
        "internalType": "uint224",
        "name": "priceToleranceRatio",
        "type": "uint224"
      },
      {
        "indexed": false,
        "internalType": "uint224",
        "name": "rentRate",
        "type": "uint224"
      },
      {
        "indexed": false,
        "internalType": "bytes32",
        "name": "powers",
        "type": "bytes32"
      }
    ],
    "name": "LogicCreated",
    "type": "event"
  },
  {
    "anonymous": false,
    "inputs": [
      {
        "indexed": true,
        "internalType": "address",
        "name": "acc",
        "type": "address"
      },
      {
        "indexed": true,
        "internalType": "uint256",
        "name": "id",
        "type": "uint256"
      }
    ],
    "name": "TokenAdded",
    "type": "event"
  },
  {
    "anonymous": false,
    "inputs": [
      {
        "indexed": true,
        "internalType": "address",
        "name": "acc",
        "type": "address"
      },
      {
        "indexed": true,
        "internalType": "uint256",
        "name": "id",
        "type": "uint256"
      }
    ],
    "name": "TokenRemoved",
    "type": "event"
  }
]
